Metadata-Version: 2.1
Name: projeto_adolfo
Version: 0.0.1
Summary: My short description
Home-page: https://github.com/adolfosorato/image-processing-package
Author: adolfosorato
Author-email: adolfosorato@outlook.com
Requires-Python: >=3.8
